README.md
functions_cache/__init__.py
functions_cache/engines/__init__.py
functions_cache/engines/base.py
functions_cache/engines/dynamodb.py
functions_cache/engines/gridfs.py
functions_cache/engines/mongo.py
functions_cache/engines/redis.py
functions_cache/engines/sqlite.py
functions_cache/engines/storage/__init__.py
functions_cache/engines/storage/dbdict.py
functions_cache/engines/storage/dynamodbdict.py
functions_cache/engines/storage/gridfspickledict.py
functions_cache/engines/storage/mongodict.py
functions_cache/engines/storage/redisdict.py
functions_cache/function_identifier.py
functions_cache-0.1.0.dist-info/LICENSE
functions_cache-0.1.0.dist-info/WHEEL
functions_cache-0.1.0.dist-info/METADATA
functions_cache-0.1.0.dist-info/RECORD
