Metadata-Version: 2.1
Name: functions-cache
Version: 0.1.0
Summary: cache functions output with auto refresh everytime you call it
Home-page: https://github.com/BalighMehrez/functions-cache
License: BSD License
Keywords: cache,persistence,threading,sqlite,redis,mongodb,gridfs,dynamodb
Author: Baligh Hatem
Author-email: balighmehrez@gmail.com
Requires-Python: >=3.6,<4.0
Classifier: License :: Other/Proprietary License
Classifier: Programming Language :: Python :: 3
Classifier: Programming Language :: Python :: 3.6
Classifier: Programming Language :: Python :: 3.7
Classifier: Programming Language :: Python :: 3.8
Classifier: Programming Language :: Python :: 3.9
Provides-Extra: docs
Provides-Extra: engines
Requires-Dist: Sphinx (==3.5.3); extra == "docs"
Requires-Dist: boto3 (>=1.15,<2.0); extra == "engines"
Requires-Dist: docutils (==0.16); extra == "docs"
Requires-Dist: m2r2 (>=0.2,<0.3); extra == "docs"
Requires-Dist: pymongo (>=3.0,<4.0); extra == "engines"
Requires-Dist: redis (>=3.0,<4.0); extra == "engines"
Requires-Dist: sphinx-autodoc-typehints (>=1.11,<2.0); extra == "docs"
Requires-Dist: sphinx-copybutton (>=0.3,<0.4); extra == "docs"
Requires-Dist: sphinx-rtd-theme (==0.5.2)
Requires-Dist: sphinxcontrib-apidoc (>=0.3,<0.4); extra == "docs"
Project-URL: Documentation, https://functions-cache.readthedocs.io
Project-URL: Repository, https://github.com/BalighMehrez/functions-cache
